pilgrimor/.github/workflows/release.yml
pilgrimor/__init__.py
pilgrimor/__main__.py
pilgrimor/abc/__init__.py
pilgrimor/abc/engine.py
pilgrimor/abc/migrator.py
pilgrimor/cli/__init__.py
pilgrimor/cli/base_cli.py
pilgrimor/cli/parser.py
pilgrimor/cli/rawsql_cli.py
pilgrimor/engine/__init__.py
pilgrimor/engine/engine.py
pilgrimor/engine/postgresql_engine.py
pilgrimor/exceptions.py
pilgrimor/migrator/__init__.py
pilgrimor/migrator/python_migrator/__init__.py
pilgrimor/migrator/rawsql_migrator/__init__.py
pilgrimor/migrator/rawsql_migrator/rawsql_migrator.py
pilgrimor/settings.py
pilgrimor/utils.py
pilgrimor-0.1.2.dist-info/entry_points.txt
pilgrimor-0.1.2.dist-info/WHEEL
pilgrimor-0.1.2.dist-info/METADATA
pilgrimor-0.1.2.dist-info/RECORD
